roi_space_datetime/__init__.py
roi_space_datetime/roi_time.py
roi_space_datetime/time_tools.py
roi_datetime_test-0.0.1.dist-info/LICENSE
roi_datetime_test-0.0.1.dist-info/METADATA
roi_datetime_test-0.0.1.dist-info/WHEEL
roi_datetime_test-0.0.1.dist-info/top_level.txt
roi_datetime_test-0.0.1.dist-info/RECORD
