Metadata-Version: 2.1
Name: roi-datetime-test
Version: 0.0.1
Summary: roi_space_datetime
Home-page: UNKNOWN
License: MIT
Keywords: roi_space_datetime
Platform: UNKNOWN
Requires-Python: >=3.5
License-File: LICENSE
Requires-Dist: pytz (==2021.1)
